<annotation>
	<folder>Sarna</folder>
	<filename>sarna_399.jpg</filename>
	<path>/home/tiago/PycharmProjects/MestradoUSPCodigos/yolo_mxnet/apple_2/image/Sarna/sarna_399.jpg</path>
	<source>
		<database>Unknown</database>
	</source>
	<size>
		<width>4000</width>
		<height>2248</height>
		<depth>3</depth>
	</size>
	<segmented>0</segmented>
	<object>
		<name>sarna</name>
		<pose>Unspecified</pose>
		<truncated>0</truncated>
		<difficult>0</difficult>
		<bndbox>
			<xmin>708</xmin>
			<ymin>1088</ymin>
			<xmax>940</xmax>
			<ymax>1344</ymax>
		</bndbox>
	</object>
	<object>
		<name>sarna</name>
		<pose>Unspecified</pose>
		<truncated>0</truncated>
		<difficult>0</difficult>
		<bndbox>
			<xmin>1270</xmin>
			<ymin>1174</ymin>
			<xmax>1499</xmax>
			<ymax>1438</ymax>
		</bndbox>
	</object>
	<object>
		<name>sarna</name>
		<pose>Unspecified</pose>
		<truncated>0</truncated>
		<difficult>0</difficult>
		<bndbox>
			<xmin>1349</xmin>
			<ymin>418</ymin>
			<xmax>1540</xmax>
			<ymax>597</ymax>
		</bndbox>
	</object>
	<object>
		<name>sarna</name>
		<pose>Unspecified</pose>
		<truncated>0</truncated>
		<difficult>0</difficult>
		<bndbox>
			<xmin>2340</xmin>
			<ymin>794</ymin>
			<xmax>2617</xmax>
			<ymax>1050</ymax>
		</bndbox>
	</object>
	<object>
		<name>sarna</name>
		<pose>Unspecified</pose>
		<truncated>0</truncated>
		<difficult>0</difficult>
		<bndbox>
			<xmin>2361</xmin>
			<ymin>1494</ymin>
			<xmax>2764</xmax>
			<ymax>1791</ymax>
		</bndbox>
	</object>
	<object>
		<name>sarna</name>
		<pose>Unspecified</pose>
		<truncated>0</truncated>
		<difficult>0</difficult>
		<bndbox>
			<xmin>2999</xmin>
			<ymin>1488</ymin>
			<xmax>3170</xmax>
			<ymax>1676</ymax>
		</bndbox>
	</object>
</annotation>
