<annotation>
	<folder>rust</folder>
	<filename>Train_1320.jpg</filename>
	<path>/home/tiago/PycharmProjects/MestradoUSPCodigos/datasets/plant-pathology-2020-fgvc7/rust/Train_1320.jpg</path>
	<source>
		<database>Unknown</database>
	</source>
	<size>
		<width>2048</width>
		<height>1365</height>
		<depth>3</depth>
	</size>
	<segmented>0</segmented>
	<object>
		<name>rust</name>
		<pose>Unspecified</pose>
		<truncated>0</truncated>
		<difficult>0</difficult>
		<bndbox>
			<xmin>570</xmin>
			<ymin>851</ymin>
			<xmax>646</xmax>
			<ymax>927</ymax>
		</bndbox>
	</object>
	<object>
		<name>rust</name>
		<pose>Unspecified</pose>
		<truncated>0</truncated>
		<difficult>0</difficult>
		<bndbox>
			<xmin>620</xmin>
			<ymin>514</ymin>
			<xmax>677</xmax>
			<ymax>580</ymax>
		</bndbox>
	</object>
	<object>
		<name>rust</name>
		<pose>Unspecified</pose>
		<truncated>0</truncated>
		<difficult>0</difficult>
		<bndbox>
			<xmin>758</xmin>
			<ymin>573</ymin>
			<xmax>810</xmax>
			<ymax>665</ymax>
		</bndbox>
	</object>
	<object>
		<name>rust</name>
		<pose>Unspecified</pose>
		<truncated>0</truncated>
		<difficult>0</difficult>
		<bndbox>
			<xmin>1236</xmin>
			<ymin>598</ymin>
			<xmax>1301</xmax>
			<ymax>708</ymax>
		</bndbox>
	</object>
	<object>
		<name>rust</name>
		<pose>Unspecified</pose>
		<truncated>0</truncated>
		<difficult>0</difficult>
		<bndbox>
			<xmin>658</xmin>
			<ymin>352</ymin>
			<xmax>720</xmax>
			<ymax>418</ymax>
		</bndbox>
	</object>
	<object>
		<name>rust</name>
		<pose>Unspecified</pose>
		<truncated>0</truncated>
		<difficult>0</difficult>
		<bndbox>
			<xmin>880</xmin>
			<ymin>287</ymin>
			<xmax>965</xmax>
			<ymax>360</ymax>
		</bndbox>
	</object>
	<object>
		<name>rust</name>
		<pose>Unspecified</pose>
		<truncated>0</truncated>
		<difficult>0</difficult>
		<bndbox>
			<xmin>952</xmin>
			<ymin>337</ymin>
			<xmax>1020</xmax>
			<ymax>419</ymax>
		</bndbox>
	</object>
	<object>
		<name>rust</name>
		<pose>Unspecified</pose>
		<truncated>0</truncated>
		<difficult>0</difficult>
		<bndbox>
			<xmin>73</xmin>
			<ymin>862</ymin>
			<xmax>125</xmax>
			<ymax>932</ymax>
		</bndbox>
	</object>
	<object>
		<name>rust</name>
		<pose>Unspecified</pose>
		<truncated>0</truncated>
		<difficult>0</difficult>
		<bndbox>
			<xmin>4</xmin>
			<ymin>667</ymin>
			<xmax>31</xmax>
			<ymax>731</ymax>
		</bndbox>
	</object>
	<object>
		<name>rust</name>
		<pose>Unspecified</pose>
		<truncated>0</truncated>
		<difficult>0</difficult>
		<bndbox>
			<xmin>3</xmin>
			<ymin>996</ymin>
			<xmax>34</xmax>
			<ymax>1065</ymax>
		</bndbox>
	</object>
</annotation>
