<annotation>
	<folder>rust</folder>
	<filename>Train_852.jpg</filename>
	<path>/home/tiago/PycharmProjects/QualificacaoMSc/codes/datasets/plant-pathology-2020-fgvc7/rust/Train_852.jpg</path>
	<source>
		<database>Unknown</database>
	</source>
	<size>
		<width>2048</width>
		<height>1365</height>
		<depth>3</depth>
	</size>
	<segmented>0</segmented>
	<object>
		<name>rust</name>
		<pose>Unspecified</pose>
		<truncated>0</truncated>
		<difficult>0</difficult>
		<bndbox>
			<xmin>659</xmin>
			<ymin>808</ymin>
			<xmax>797</xmax>
			<ymax>896</ymax>
		</bndbox>
	</object>
	<object>
		<name>rust</name>
		<pose>Unspecified</pose>
		<truncated>0</truncated>
		<difficult>0</difficult>
		<bndbox>
			<xmin>1072</xmin>
			<ymin>472</ymin>
			<xmax>1233</xmax>
			<ymax>639</ymax>
		</bndbox>
	</object>
	<object>
		<name>rust</name>
		<pose>Unspecified</pose>
		<truncated>0</truncated>
		<difficult>0</difficult>
		<bndbox>
			<xmin>1289</xmin>
			<ymin>389</ymin>
			<xmax>1413</xmax>
			<ymax>572</ymax>
		</bndbox>
	</object>
</annotation>
